{"chunk_definitions":[{"row":68,"row_count":1,"visible":true,"expansion_state":0,"options":{"engine":"r","label":"setup","include":false},"document_id":"0A28B952","chunk_id":"csetup_chunk","chunk_label":"setup"},{"row":274,"row_count":1,"visible":true,"expansion_state":0,"options":{"engine":"r","echo":false,"message":false,"warning":false,"label":"unnamed-chunk-133"},"document_id":"0A28B952","chunk_id":"cx2k03a4w9s8p","chunk_label":"unnamed-chunk-1"},{"row":321,"row_count":1,"visible":true,"expansion_state":0,"options":{"engine":"r","label":"unnamed-chunk-126"},"document_id":"0A28B952","chunk_id":"chr5ot34zt749","chunk_label":"unnamed-chunk-2"},{"row":345,"row_count":1,"visible":true,"expansion_state":0,"options":{"engine":"r","echo":false,"message":false,"warning":false,"label":"unnamed-chunk-130"},"document_id":"0A28B952","chunk_id":"coc4dlxilltji","chunk_label":"unnamed-chunk-3"},{"row":369,"row_count":1,"visible":true,"expansion_state":0,"options":{"engine":"r","label":"unnamed-chunk-131"},"document_id":"0A28B952","chunk_id":"cv21eumfrx6qh","chunk_label":"unnamed-chunk-4"},{"row":522,"row_count":1,"visible":true,"expansion_state":0,"options":{"engine":"r","label":"unnamed-chunk-94"},"document_id":"0A28B952","chunk_id":"cv46prdfl8eac","chunk_label":"unnamed-chunk-8"},{"row":605,"row_count":1,"visible":true,"expansion_state":0,"options":{"engine":"r","echo":false,"message":false,"warning":false,"label":"unnamed-chunk-75"},"document_id":"0A28B952","chunk_id":"czgguld50dazg","chunk_label":"unnamed-chunk-9"},{"row":614,"row_count":1,"visible":true,"expansion_state":0,"options":{"engine":"r","label":"unnamed-chunk-74"},"document_id":"0A28B952","chunk_id":"ctg9qmktjneho","chunk_label":"unnamed-chunk-10"},{"row":736,"row_count":1,"visible":true,"expansion_state":0,"options":{"engine":"r","echo":false,"message":false,"warning":false,"label":"unnamed-chunk-95"},"document_id":"0A28B952","chunk_id":"co88egotkom6e","chunk_label":"unnamed-chunk-13"}],"doc_write_time":1621372077,"working_dir":null,"default_chunk_options":{},"chunk_rendered_width":700}